superpipe/__init__.py
superpipe/clients.py
superpipe/config.py
superpipe/grid_search.py
superpipe/llm.py
superpipe/models.py
superpipe/pipeline.py
superpipe/pydantic.py
superpipe/steps/__init__.py
superpipe/steps/custom.py
superpipe/steps/embedding_search.py
superpipe/steps/llm_step.py
superpipe/steps/llm_structured.py
superpipe/steps/llm_structured_composite.py
superpipe/steps/serp.py
superpipe/steps/step.py
superpipe/steps/utils.py
superpipe/util.py
superpipe_py-0.1.9.dist-info/METADATA
superpipe_py-0.1.9.dist-info/WHEEL
superpipe_py-0.1.9.dist-info/RECORD
