Metadata-Version: 2.1
Name: superpipe-py
Version: 0.1.9
Summary: build unstructured to structured data transformation pipelines
Home-page: https://github.com/villagecomputing/superpipe
License: MIT
Author: Aman Dhesi
Author-email: aman@stelolabs.com
Requires-Python: >=3.10,<4.0
Classifier: License :: OSI Approved :: MIT License
Classifier: Programming Language :: Python :: 3
Classifier: Programming Language :: Python :: 3.10
Classifier: Programming Language :: Python :: 3.11
Requires-Dist: anthropic (>=0.21.3,<0.22.0)
Requires-Dist: faiss-cpu (>=1.7.4,<2.0.0)
Requires-Dist: numpy (>=1.26.2,<2.0.0)
Requires-Dist: openai (>=1.3.9,<2.0.0)
Requires-Dist: pandas (>=2.1.4,<3.0.0)
Requires-Dist: prettytable (>=3.10.0,<4.0.0)
Requires-Dist: pydantic (>=2.6.1,<3.0.0)
Requires-Dist: requests (>=2.31.0,<3.0.0)
Project-URL: Repository, https://github.com/villagecomputing/superpipe
